minerva_ufrj/__init__.py
minerva_ufrj/__main__.py
minerva_ufrj/minerva.py
minerva_ufrj-1.2.0.data/data/minerva_data/.minerva-info
minerva_ufrj-1.2.0.data/scripts/minerva
minerva_ufrj-1.2.0.dist-info/LICENSE
minerva_ufrj-1.2.0.dist-info/METADATA
minerva_ufrj-1.2.0.dist-info/WHEEL
minerva_ufrj-1.2.0.dist-info/entry_points.txt
minerva_ufrj-1.2.0.dist-info/top_level.txt
minerva_ufrj-1.2.0.dist-info/RECORD
