Metadata-Version: 2.1
Name: minerva-ufrj
Version: 1.2.0
Summary: Book-renewal project for UFRJ library users
Home-page: https://www.lam.ufrj.br/~pmxavier/projects/minerva/
Author: Pedro Maciel Xavier
Author-email: pedromxavier@poli.ufrj.br
License: UNKNOWN
Project-URL: Bug Tracker, https://github.com/pedromxavier/minerva/issues
Project-URL: Source, https://github.com/pedromxavier/minerva
Platform: UNKNOWN
Classifier: Intended Audience :: Education
Classifier: Programming Language :: Python :: 3.7
Classifier: Programming Language :: Python :: 3.8
Classifier: License :: OSI Approved :: MIT License
Classifier: Operating System :: Microsoft :: Windows
Classifier: Operating System :: POSIX :: Linux
Classifier: Operating System :: MacOS :: MacOS X
Requires-Python: <4,>=3.7
Requires-Dist: keyring
